{
  "claim_id": "SFT-COMP-DIST-COMMUNICATION-001",
  "controls": [
    {
      "expected_behavior": "reject the generated form lacking complete first-axis coverage",
      "kind": "false_premise",
      "observed_behavior": "anonymous-or-partial-processes removes a required exact processes condition.",
      "passed": true,
      "receipt_hash": "sha256:7df8e76d91036aa4d9c043bc617af8b6ba5eebcda43b56f7ca402b8949d27edc"
    },
    {
      "expected_behavior": "reject a changed official source identity",
      "kind": "tampered_source",
      "observed_behavior": "changed source identity differs",
      "passed": true,
      "receipt_hash": "sha256:40873481e30f9a558a4957b4ad283250d4d78b0085182f34b5d0cae7f50ba71d"
    },
    {
      "expected_behavior": "reject missing, duplicated or additional survivors",
      "kind": "tampered_artifact",
      "observed_behavior": "literal product contains one survivor and unique identities",
      "passed": true,
      "receipt_hash": "sha256:7bf67fbeeb98c7c20892c4575b6a863bce8e693bdb9430ed8793b1e1ef212be6"
    },
    {
      "expected_behavior": "halt imported models, parameters or excluded quantum machinery",
      "kind": "boundary",
      "observed_behavior": "no conventional machine, algorithm, language, security definition or learning model may select the law; no numerical zero, negative, irrational, imaginary or floating proof quantity; no completed infinity or ungenerated continuum; no free, fitted or learned parameter; no application result or pretrained model; Reliability, ordering and delay are separate declared channel properties.",
      "passed": true,
      "receipt_hash": "sha256:ecb34f6215dc73247313bd3a31d75b00e40d59a092741aa7bb5a53c7a4069b6c"
    }
  ]
}
