{
  "accepted_evidence": true,
  "claim_id": "SFT-PHYS-MATTER-PARTICLE-ANTIPARTICLE-001",
  "closure_status": "depth_independent",
  "derivation_seal_hash": "sha256:d0c020e5bbbb2a863a14652173767dc88149cef47ddfbf32699d56cc043b5601",
  "empirical_validation_hash": "sha256:21fadf4dd9de421fc4ef535a9d2f551fb9dfd5d59a0365c85c79cff5d3f8dd1b",
  "engine_id": "sft-v3-single-admission-engine/1",
  "external_status": "empirically_tested_and_independently_replicated",
  "external_validation_hash": "sha256:861e1634065625f513cfc6fb505d7e7d77493a092f049c219057f75b4be87da7",
  "gate_results": [
    {
      "detail": "one theorem, no axioms, zero free parameters and admitted dependencies",
      "gate": "registration",
      "passed": true
    },
    {
      "detail": "generated candidate census matches its registered complete boundary",
      "gate": "enumeration",
      "passed": true
    },
    {
      "detail": "every generated candidate decided and exactly one survivor remains",
      "gate": "forcing",
      "passed": true
    },
    {
      "detail": "minimality and named-shape uniqueness established at the exact boundary",
      "gate": "form_closure",
      "passed": true
    },
    {
      "detail": "all required false, tampered and boundary controls behaved as registered",
      "gate": "controls",
      "passed": true
    },
    {
      "detail": "derivation, census, closure and controls sealed",
      "gate": "seal",
      "passed": true
    },
    {
      "detail": "distinct implementation recomputed the sealed result from declared inputs",
      "gate": "independent_validation",
      "passed": true
    },
    {
      "detail": "target-inaccessible prediction sealed before independent data measurement",
      "gate": "empirical_validation",
      "passed": true
    },
    {
      "detail": "closed law may become a dependency",
      "gate": "model_admission",
      "passed": true
    }
  ],
  "halted_stage": null,
  "model_admitted": true,
  "receipt_hash": "sha256:4840b7076ad83c2c76882af2e81a8309d6ee80028e61796c2f91a896fea2ebfd",
  "violations": []
}
