{
  "accepted_evidence": true,
  "claim_id": "SFT-PHYS-CONDENSED-SUPERCONDUCTIVITY-001",
  "closure_status": "depth_independent",
  "derivation_seal_hash": "sha256:06e4517ff4a130b52a47147c077429df7e15957c2a80e5c5b067afa9b4297fd8",
  "empirical_validation_hash": "sha256:6251be4d6b6ee93d576f77e76672172a19d45db415dd21fee237071438ad1258",
  "engine_id": "sft-v3-single-admission-engine/1",
  "external_status": "empirically_tested_and_independently_replicated",
  "external_validation_hash": "sha256:77d8527a95cce3821e1c646a21720aa374cd5365ceff4eddd7e275b946be1cc8",
  "gate_results": [
    {
      "detail": "one theorem, no axioms, zero free parameters and admitted dependencies",
      "gate": "registration",
      "passed": true
    },
    {
      "detail": "generated candidate census matches its registered complete boundary",
      "gate": "enumeration",
      "passed": true
    },
    {
      "detail": "every generated candidate decided and exactly one survivor remains",
      "gate": "forcing",
      "passed": true
    },
    {
      "detail": "minimality and named-shape uniqueness established at the exact boundary",
      "gate": "form_closure",
      "passed": true
    },
    {
      "detail": "all required false, tampered and boundary controls behaved as registered",
      "gate": "controls",
      "passed": true
    },
    {
      "detail": "derivation, census, closure and controls sealed",
      "gate": "seal",
      "passed": true
    },
    {
      "detail": "distinct implementation recomputed the sealed result from declared inputs",
      "gate": "independent_validation",
      "passed": true
    },
    {
      "detail": "target-inaccessible prediction sealed before independent data measurement",
      "gate": "empirical_validation",
      "passed": true
    },
    {
      "detail": "closed law may become a dependency",
      "gate": "model_admission",
      "passed": true
    }
  ],
  "halted_stage": null,
  "model_admitted": true,
  "receipt_hash": "sha256:ee86d5d893add989390c63fcc6f11bc7d95e0dc8c9c7dabd724c3233931deb04",
  "violations": []
}
