{
  "accepted_evidence": true,
  "claim_id": "SFT-QUANTUM-ERROR-CORRECTION-001",
  "closure_status": "depth_independent",
  "derivation_seal_hash": "sha256:61cc113c2d425a9f9c9d2e13bb1a983bd94e88220a6d91a4f1815d41b5059ee6",
  "empirical_validation_hash": null,
  "engine_id": "sft-v3-single-admission-engine/1",
  "external_status": "independently_replicated",
  "external_validation_hash": "sha256:c5784b25becf3d48609c4a3447a3cff73cd2822418dd3800282d1948dbe6d3ef",
  "gate_results": [
    {
      "detail": "one theorem, no axioms, zero free parameters and admitted dependencies",
      "gate": "registration",
      "passed": true
    },
    {
      "detail": "generated candidate census matches its registered complete boundary",
      "gate": "enumeration",
      "passed": true
    },
    {
      "detail": "every generated candidate decided and exactly one survivor remains",
      "gate": "forcing",
      "passed": true
    },
    {
      "detail": "minimality and named-shape uniqueness established at the exact boundary",
      "gate": "form_closure",
      "passed": true
    },
    {
      "detail": "all required false, tampered and boundary controls behaved as registered",
      "gate": "controls",
      "passed": true
    },
    {
      "detail": "derivation, census, closure and controls sealed",
      "gate": "seal",
      "passed": true
    },
    {
      "detail": "distinct implementation recomputed the sealed result from declared inputs",
      "gate": "independent_validation",
      "passed": true
    },
    {
      "detail": "closed law may become a dependency",
      "gate": "model_admission",
      "passed": true
    }
  ],
  "halted_stage": null,
  "model_admitted": true,
  "receipt_hash": "sha256:a4791dcbf8753c32e8304c5d5e80f9bf7f21a7356b6adb9422ea60d5eaf59656",
  "violations": []
}
