{
  "accepted_evidence": true,
  "claim_id": "SFT-INFO-CODING-001",
  "closure_status": "depth_independent",
  "derivation_seal_hash": "sha256:357b7cd32f117b55c0bad9606247bf12db72c82b999710d1c38698a5d895523d",
  "empirical_validation_hash": null,
  "engine_id": "sft-v3-single-admission-engine/1",
  "external_status": "independently_replicated",
  "external_validation_hash": "sha256:d1be5779eb0de948cc041a05e504a3dc9bb66fba0985f16bf5ed8d015fdc6a66",
  "gate_results": [
    {
      "detail": "one theorem, no axioms, zero free parameters and admitted dependencies",
      "gate": "registration",
      "passed": true
    },
    {
      "detail": "generated candidate census matches its registered complete boundary",
      "gate": "enumeration",
      "passed": true
    },
    {
      "detail": "every generated candidate decided and exactly one survivor remains",
      "gate": "forcing",
      "passed": true
    },
    {
      "detail": "minimality and named-shape uniqueness established at the exact boundary",
      "gate": "form_closure",
      "passed": true
    },
    {
      "detail": "all required false, tampered and boundary controls behaved as registered",
      "gate": "controls",
      "passed": true
    },
    {
      "detail": "derivation, census, closure and controls sealed",
      "gate": "seal",
      "passed": true
    },
    {
      "detail": "distinct implementation recomputed the sealed result from declared inputs",
      "gate": "independent_validation",
      "passed": true
    },
    {
      "detail": "closed law may become a dependency",
      "gate": "model_admission",
      "passed": true
    }
  ],
  "halted_stage": null,
  "model_admitted": true,
  "receipt_hash": "sha256:7c7648bdba686025c8b1f647b3e63a242da24234aa953cac184021f878b07711",
  "violations": []
}
