{
  "accepted_evidence": true,
  "claim_id": "SFT-MATH-COMBINATORICS-001",
  "closure_status": "depth_independent",
  "derivation_seal_hash": "sha256:3177572ea372062f65a7969fdf4e498c86c9af558e37c048165e1d950cf1d942",
  "empirical_validation_hash": null,
  "engine_id": "sft-v3-single-admission-engine/1",
  "external_status": "independently_replicated",
  "external_validation_hash": "sha256:dbfc2711bbabde9be3bf4a4cc3c5de3cd62440c9fbeea20b2fceed6dcfb1275b",
  "gate_results": [
    {
      "detail": "one theorem, no axioms, zero free parameters and admitted dependencies",
      "gate": "registration",
      "passed": true
    },
    {
      "detail": "generated candidate census matches its registered complete boundary",
      "gate": "enumeration",
      "passed": true
    },
    {
      "detail": "every generated candidate decided and exactly one survivor remains",
      "gate": "forcing",
      "passed": true
    },
    {
      "detail": "minimality and named-shape uniqueness established at the exact boundary",
      "gate": "form_closure",
      "passed": true
    },
    {
      "detail": "all required false, tampered and boundary controls behaved as registered",
      "gate": "controls",
      "passed": true
    },
    {
      "detail": "derivation, census, closure and controls sealed",
      "gate": "seal",
      "passed": true
    },
    {
      "detail": "distinct implementation recomputed the sealed result from declared inputs",
      "gate": "independent_validation",
      "passed": true
    },
    {
      "detail": "closed law may become a dependency",
      "gate": "model_admission",
      "passed": true
    }
  ],
  "halted_stage": null,
  "model_admitted": true,
  "receipt_hash": "sha256:52e1db94bb7865270bb3387c47c609c438de3338b542cc31d910b981e4250968",
  "violations": []
}
