{
  "accepted_evidence": true,
  "claim_id": "SFT-PHYS-SPACETIME-INTERVAL-001",
  "closure_status": "depth_independent",
  "derivation_seal_hash": "sha256:fec28317c8170661e758a9419a98c1debf2cb1ab1c4166cc27c45d6f6e79b004",
  "empirical_validation_hash": "sha256:2a2776461015bd10876a20724e3935b290f458bf6725d340951e4114c8b2ca6f",
  "engine_id": "sft-v3-single-admission-engine/1",
  "external_status": "empirically_tested_and_independently_replicated",
  "external_validation_hash": "sha256:77aaa397de56081eb78d5310378433bd205de1868243de36e40d7ea95d1d2362",
  "gate_results": [
    {
      "detail": "one theorem, no axioms, zero free parameters and admitted dependencies",
      "gate": "registration",
      "passed": true
    },
    {
      "detail": "generated candidate census matches its registered complete boundary",
      "gate": "enumeration",
      "passed": true
    },
    {
      "detail": "every generated candidate decided and exactly one survivor remains",
      "gate": "forcing",
      "passed": true
    },
    {
      "detail": "minimality and named-shape uniqueness established at the exact boundary",
      "gate": "form_closure",
      "passed": true
    },
    {
      "detail": "all required false, tampered and boundary controls behaved as registered",
      "gate": "controls",
      "passed": true
    },
    {
      "detail": "derivation, census, closure and controls sealed",
      "gate": "seal",
      "passed": true
    },
    {
      "detail": "distinct implementation recomputed the sealed result from declared inputs",
      "gate": "independent_validation",
      "passed": true
    },
    {
      "detail": "target-inaccessible prediction sealed before independent data measurement",
      "gate": "empirical_validation",
      "passed": true
    },
    {
      "detail": "closed law may become a dependency",
      "gate": "model_admission",
      "passed": true
    }
  ],
  "halted_stage": null,
  "model_admitted": true,
  "receipt_hash": "sha256:50d120a00b976766cf5679b950c5b17e11f3c7718e90f8350bfb0f4de166298f",
  "violations": []
}
