{
  "branch_id": "information_science",
  "frozen": true,
  "current_knowledge_scope": "V3 clean-room Information Science forced from the admitted Foundation and Mathematics branches: symbols and distinguishability; encoding and decoding; exact information quantity; entropy and uncertainty; compression and redundancy; finite channels and capacity; noise and error; exact finite coding; mutual and conditional information; information conservation, loss and transformation; classical and probabilistic information correspondence; and finite quantum-information support correspondence.",
  "required_claim_ids": [
    "SFT-INFO-SYMBOL-DISTINCTION-001",
    "SFT-INFO-ENCODING-DECODING-001",
    "SFT-INFO-QUANTITY-001",
    "SFT-INFO-ENTROPY-UNCERTAINTY-001",
    "SFT-INFO-COMPRESSION-REDUNDANCY-001",
    "SFT-INFO-CHANNEL-CAPACITY-001",
    "SFT-INFO-NOISE-ERROR-001",
    "SFT-INFO-CODING-001",
    "SFT-INFO-MUTUAL-CONDITIONAL-001",
    "SFT-INFO-CONSERVATION-LOSS-001",
    "SFT-INFO-CLASSICAL-PROBABILISTIC-001",
    "SFT-INFO-QUANTUM-CORRESPONDENCE-001"
  ],
  "unclassified_obligations": [],
  "frontier_obligations": [],
  "inventory_hash": "sha256:98162a98e2508cb36381ed2b99cb195e3cc7e1b33b8577d4c5a4550a492a0b17"
}
